_trace_skeleton.cpython-39-darwin.so
trace_skeleton.py
trace_skeleton-0.1.6.dist-info/METADATA
trace_skeleton-0.1.6.dist-info/WHEEL
trace_skeleton-0.1.6.dist-info/top_level.txt
trace_skeleton-0.1.6.dist-info/RECORD
