Metadata-Version: 2.1
Name: trace-skeleton
Version: 0.1.6
Summary: Trace and label skeleton of a 2D image.
Author: Imad Toubal
Author-email: Imad Toubal <imad.toubal@gmail.com>
Project-URL: Homepage, https://github.com/imadtoubal/trace-skeleton
Project-URL: Bug Tracker, https://github.com/imadtoubal/trace-skeleton/issues
Classifier: Programming Language :: Python :: 3
Classifier: License :: OSI Approved :: MIT License
Classifier: Operating System :: OS Independent
Requires-Python: >=3.6
